{
  "project_info": {
    "project_number": "497490603741",
    "project_id": "lost-mud",
    "storage_bucket": "lost-mud.firebasestorage.app"
  },
  "client": [
    {
      "client_info": {
        "mobilesdk_app_id": "1:497490603741:android:aa8a14e32bf468f1667534",
        "android_client_info": {
          "package_name": "com.example.flutter_rpg"
        }
      },
      "oauth_client": [],
      "api_key": [
        {
          "current_key": "AIzaSyAHclK3-uvIWTAIU4G5DNBaiS_SOf7D4rk"
        }
      ],
      "services": {
        "appinvite_service": {
          "other_platform_oauth_client": []
        }
      }
    }
  ],
  "configuration_version": "1"
}